AdvancedFernetDataEncryption.py
advancedfernetdataencryption-1.1.dist-info/METADATA
advancedfernetdataencryption-1.1.dist-info/WHEEL
advancedfernetdataencryption-1.1.dist-info/licenses/LICENSE
advancedfernetdataencryption-1.1.dist-info/RECORD
