Metadata-Version: 2.1
Name: AdvancedFernetDataEncryption
Version: 1.1
Summary: An encryption that uses the Fernet assymetric key generator and random values to create a secure token and key that can be stored and still be unreadable to any user.
Project-URL: Homepage, https://github.com/garfield8123/AdvancedFernetDataEncryption
Project-URL: Bug Tracker, https://github.com/garfield8123/AdvancedFernetDataEncryption/issues
Author-email: garfield8123 <garfield8123@gmail.com>
License-File: LICENSE
Classifier: License :: OSI Approved :: MIT License
Classifier: Operating System :: OS Independent
Classifier: Programming Language :: Python :: 3
Requires-Python: >=3.5
